vt2pbf/__init__.py
vt2pbf/config.py
vt2pbf/encoder.py
vt2pbf/exceptions.py
vt2pbf/mapbox/__init__.py
vt2pbf/mapbox/vector_tile.proto
vt2pbf/mapbox/protobuf_3/__init__.py
vt2pbf/mapbox/protobuf_3/vector_tile_pb2.py
vt2pbf/mapbox/protobuf_4/__init__.py
vt2pbf/mapbox/protobuf_4/vector_tile_pb2.py
vt2pbf/mapbox/protobuf_4/vector_tile_pb2.pyi
vt2pbf/mapbox/protobuf_5/__init__.py
vt2pbf/mapbox/protobuf_5/vector_tile_pb2.py
vt2pbf/mapbox/protobuf_6/__init__.py
vt2pbf/mapbox/protobuf_6/vector_tile_pb2.py
vt2pbf/service/__init__.py
vt2pbf/service/feature.py
vt2pbf/service/layer.py
vt2pbf/service/tile.py
vt2pbf-0.2.0.dist-info/METADATA
vt2pbf-0.2.0.dist-info/WHEEL
vt2pbf-0.2.0.dist-info/licenses/LICENSE
vt2pbf-0.2.0.dist-info/RECORD
