Metadata-Version: 2.4
Name: vt2pbf
Version: 0.2.0
Summary: Python library for encoding mapbox vector tiles into tile_pbf
Project-URL: Homepage, https://github.com/DenysMoskalenko/vt2pbf
Author: DenysMoskalenko
License: MIT
License-File: LICENSE
Requires-Python: >=3.7
Requires-Dist: protobuf<7,>=3.7.0
Provides-Extra: dev
Requires-Dist: coverage<7,>=6; extra == 'dev'
Requires-Dist: pytest<8,>=7; extra == 'dev'
Requires-Dist: ruff>=0.13.2; extra == 'dev'
